MANIFEST.in
README.md
requirements.txt
setup.cfg
setup.py
versioneer.py
botcity/plugins/excel/__init__.py
botcity/plugins/excel/_version.py
botcity/plugins/excel/plugin.py
botcity_excel_plugin.egg-info/PKG-INFO
botcity_excel_plugin.egg-info/SOURCES.txt
botcity_excel_plugin.egg-info/dependency_links.txt
botcity_excel_plugin.egg-info/requires.txt
botcity_excel_plugin.egg-info/top_level.txt
tests/test_import.py
tests/test_plugin.py