Metadata-Version: 2.1
Name: botcity-excel-plugin
Version: 0.1.7
Home-page: https://bitbucket.org/botcitydev/bot-excel-plugin-python.git
Requires-Python: >=3.7
